[
    {
        "type": "recipe",
        "result": "faction_base_modular_workshop_room0_rock_northeast",
        "description": "We can use a rock workshop.  Let's start by building a spot to protect the workers from the rain.",
        "category": "CC_BUILDING",
        "subcategory": "CSC_BUILDING_BASES",
        "autolearn": false,
        "never_learn": true,
        "construction_blueprint": "fbmw_room0_rock_northeast",
        "blueprint_name": "northeast wall",
        "blueprint_requires": [
            {
                "id": "fbmw_0"
            }
        ],
        "blueprint_provides": [
            {
                "id": "fbmw_northeast"
            }
        ],
        "blueprint_excludes": [
            {
                "id": "fbmw_northeast"
            }
        ],
        "blueprint_needs": {
            "time": "1 s",
            "skills": [
                [
                    "fabrication",
                    6
                ],
                [
                    "survival",
                    2
                ]
            ],
            "inline": {
                "tools": [],
                "qualities": [
                    [
                        {
                            "id": "DIG",
                            "level": 2
                        }
                    ],
                    [
                        {
                            "id": "HAMMER",
                            "level": 2
                        }
                    ],
                    [
                        {
                            "id": "SAW_W",
                            "level": 2
                        }
                    ]
                ],
                "components": [
                    [
                        [
                            "2x4",
                            57
                        ]
                    ],
                    [
                        [
                            "glass_sheet",
                            1
                        ]
                    ],
                    [
                        [
                            "mortar_build",
                            4
                        ]
                    ],
                    [
                        [
                            "nail",
                            140
                        ]
                    ],
                    [
                        [
                            "pebble",
                            112
                        ]
                    ],
                    [
                        [
                            "rock",
                            54
                        ]
                    ],
                    [
                        [
                            "wood_panel",
                            6
                        ]
                    ]
                ]
            }
        }
    },
    {
        "type": "recipe",
        "result": "faction_base_modular_workshop_room3_rock_north",
        "description": "Let's extend the north rock wall to the west and add some storage space.",
        "category": "CC_BUILDING",
        "subcategory": "CSC_BUILDING_BASES",
        "autolearn": false,
        "never_learn": true,
        "construction_blueprint": "fbmw_room3_rock_north",
        "blueprint_name": "north wall",
        "blueprint_requires": [
            {
                "id": "fbmw_northeast",
                "amount": 3
            }
        ],
        "blueprint_provides": [
            {
                "id": "fbmw_north"
            }
        ],
        "blueprint_excludes": [
            {
                "id": "fbmw_north"
            }
        ],
        "blueprint_needs": {
            "time": "1 s",
            "skills": [
                [
                    "fabrication",
                    6
                ],
                [
                    "survival",
                    2
                ]
            ],
            "inline": {
                "tools": [],
                "qualities": [
                    [
                        {
                            "id": "DIG",
                            "level": 2
                        }
                    ],
                    [
                        {
                            "id": "HAMMER",
                            "level": 2
                        }
                    ],
                    [
                        {
                            "id": "SAW_W",
                            "level": 2
                        }
                    ]
                ],
                "components": [
                    [
                        [
                            "2x4",
                            32
                        ]
                    ],
                    [
                        [
                            "nail",
                            98
                        ]
                    ],
                    [
                        [
                            "wood_panel",
                            5
                        ]
                    ],
                    [
                        [
                            "hinge",
                            1
                        ]
                    ],
                    [
                        [
                            "glass_sheet",
                            1
                        ]
                    ],
                    [
                        [
                            "rock",
                            36
                        ]
                    ],
                    [
                        [
                            "pebble",
                            75
                        ]
                    ],
                    [
                        [
                            "mortar_build",
                            3
                        ]
                    ]
                ]
            }
        }
    },
    {
        "type": "recipe",
        "result": "faction_base_modular_workshop_room4_rock_east",
        "description": "Let's expand our production by adding another charcoal kiln.",
        "category": "CC_BUILDING",
        "subcategory": "CSC_BUILDING_BASES",
        "autolearn": false,
        "never_learn": true,
        "construction_blueprint": "fbmw_room4_rock_east",
        "blueprint_name": "east forage wall",
        "blueprint_requires": [
            {
                "id": "fbmw_north"
            }
        ],
        "blueprint_provides": [
            {
                "id": "fbmw_east"
            },
            {
                "id": "blacksmith_recipes_3"
            }
        ],
        "blueprint_excludes": [
            {
                "id": "fbmw_east"
            }
        ],
        "blueprint_needs": {
            "time": "1 s",
            "skills": [
                [
                    "fabrication",
                    6
                ],
                [
                    "survival",
                    2
                ]
            ],
            "inline": {
                "tools": [],
                "qualities": [
                    [
                        {
                            "id": "DIG",
                            "level": 2
                        }
                    ],
                    [
                        {
                            "id": "HAMMER",
                            "level": 2
                        }
                    ],
                    [
                        {
                            "id": "SAW_W",
                            "level": 2
                        }
                    ]
                ],
                "components": [
                    [
                        [
                            "2x4",
                            70
                        ]
                    ],
                    [
                        [
                            "nail",
                            186
                        ]
                    ],
                    [
                        [
                            "wood_panel",
                            9
                        ]
                    ],
                    [
                        [
                            "hinge",
                            1
                        ]
                    ],
                    [
                        [
                            "rock",
                            34
                        ]
                    ],
                    [
                        [
                            "glass_sheet",
                            1
                        ]
                    ],
                    [
                        [
                            "pebble",
                            50
                        ]
                    ],
                    [
                        [
                            "mortar_build",
                            2
                        ]
                    ]
                ]
            }
        }
    },
    {
        "type": "recipe",
        "result": "faction_base_modular_workshop_room5_rock_center",
        "description": "Let's expand work area with a rock wall, and add add a bookshelf for our reference books.",
        "category": "CC_BUILDING",
        "subcategory": "CSC_BUILDING_BASES",
        "autolearn": false,
        "never_learn": true,
        "construction_blueprint": "fbmw_room5_rock_center",
        "blueprint_name": "west forage wall",
        "blueprint_requires": [
            {
                "id": "fbmw_east"
            }
        ],
        "blueprint_provides": [
            {
                "id": "fbmw_center"
            }
        ],
        "blueprint_excludes": [
            {
                "id": "fbmw_center"
            }
        ],
        "blueprint_needs": {
            "time": "1 s",
            "skills": [
                [
                    "fabrication",
                    6
                ],
                [
                    "survival",
                    2
                ],
                [
                    "tailor",
                    3
                ]
            ],
            "inline": {
                "tools": [],
                "qualities": [
                    [
                        {
                            "id": "DIG",
                            "level": 2
                        }
                    ],
                    [
                        {
                            "id": "HAMMER",
                            "level": 2
                        }
                    ],
                    [
                        {
                            "id": "SAW_W",
                            "level": 2
                        }
                    ]
                ],
                "components": [
                    [
                        [
                            "2x4",
                            38
                        ]
                    ],
                    [
                        [
                            "blanket",
                            1
                        ],
                        [
                            "down_blanket",
                            1
                        ],
                        [
                            "fur_blanket",
                            1
                        ]
                    ],
                    [
                        [
                            "glass_sheet",
                            1
                        ]
                    ],
                    [
                        [
                            "mortar_build",
                            2
                        ]
                    ],
                    [
                        [
                            "nail",
                            93
                        ]
                    ],
                    [
                        [
                            "pebble",
                            50
                        ]
                    ],
                    [
                        [
                            "rock",
                            24
                        ]
                    ],
                    [
                        [
                            "wood_panel",
                            4
                        ]
                    ]
                ]
            }
        }
    },
    {
        "type": "recipe",
        "result": "faction_base_modular_workshop_room6_rock_north",
        "description": "Let's expand our production by adding a rock walled pottery kiln area.",
        "category": "CC_BUILDING",
        "subcategory": "CSC_BUILDING_BASES",
        "autolearn": false,
        "never_learn": true,
        "construction_blueprint": "fbmw_room6_rock_north",
        "blueprint_name": "north pottery wall",
        "blueprint_requires": [
            {
                "id": "fbmw_center"
            }
        ],
        "blueprint_provides": [
            {
                "id": "fbmw_north"
            },
            {
                "id": "blacksmith_recipes_4"
            }
        ],
        "blueprint_excludes": [
            {
                "id": "fbmw_north",
                "amount": 2
            }
        ],
        "blueprint_resources": [
            "tongs",
            "chisel",
            "hammer",
            "swage"
        ],
        "components": [
            [
                [
                    "tongs",
                    1
                ]
            ],
            [
                [
                    "chisel",
                    1
                ]
            ],
            [
                [
                    "hammer",
                    1
                ]
            ],
            [
                [
                    "swage",
                    1
                ]
            ]
        ],
        "blueprint_needs": {
            "time": "1 s",
            "skills": [
                [
                    "fabrication",
                    6
                ],
                [
                    "survival",
                    2
                ]
            ],
            "inline": {
                "tools": [
                    [
                        [
                            "oxy_torch",
                            20
                        ],
                        [
                            "toolset",
                            150
                        ],
                        [
                            "welder",
                            100
                        ],
                        [
                            "welder_crude",
                            150
                        ]
                    ]
                ],
                "qualities": [
                    [
                        {
                            "id": "DIG",
                            "level": 2
                        }
                    ],
                    [
                        {
                            "id": "GLARE",
                            "level": 2
                        }
                    ],
                    [
                        {
                            "id": "HAMMER",
                            "level": 2
                        }
                    ],
                    [
                        {
                            "id": "SAW_W",
                            "level": 2
                        }
                    ]
                ],
                "components": [
                    [
                        [
                            "2x4",
                            33
                        ]
                    ],
                    [
                        [
                            "mortar_build",
                            1
                        ]
                    ],
                    [
                        [
                            "nail",
                            95
                        ]
                    ],
                    [
                        [
                            "pebble",
                            37
                        ]
                    ],
                    [
                        [
                            "pipe",
                            4
                        ]
                    ],
                    [
                        [
                            "rock",
                            28
                        ]
                    ],
                    [
                        [
                            "sheet_metal",
                            1
                        ]
                    ],
                    [
                        [
                            "sheet_metal_small",
                            2
                        ]
                    ],
                    [
                        [
                            "water",
                            1
                        ],
                        [
                            "water_clean",
                            1
                        ]
                    ],
                    [
                        [
                            "wood_panel",
                            5
                        ]
                    ]
                ]
            }
        }
    },
    {
        "type": "recipe",
        "result": "faction_base_modular_workshop_room7to9_rock_northwest",
        "description": "Let's enclose this pottery with rock walls and get some more storage set up.",
        "category": "CC_BUILDING",
        "subcategory": "CSC_BUILDING_BASES",
        "autolearn": false,
        "never_learn": true,
        "construction_blueprint": "fbmw_room7to9_rock_northwest",
        "blueprint_name": "northwest and south pottery wall",
        "blueprint_requires": [
            {
                "id": "fbmw_north",
                "amount": 2
            }
        ],
        "blueprint_provides": [
            {
                "id": "fbmw_northwest"
            },
            {
                "id": "blacksmith_recipes_5"
            }
        ],
        "blueprint_excludes": [
            {
                "id": "fbmw_northwest"
            }
        ],
        "blueprint_needs": {
            "time": "1 s",
            "skills": [
                [
                    "fabrication",
                    6
                ],
                [
                    "survival",
                    2
                ]
            ],
            "inline": {
                "tools": [
                    [
                        [
                            "machete",
                            -1
                        ],
                        [
                            "makeshift_machete",
                            -1
                        ],
                        [
                            "scythe",
                            -1
                        ],
                        [
                            "sickle",
                            -1
                        ],
                        [
                            "survivor_machete",
                            -1
                        ]
                    ]
                ],
                "qualities": [
                    [
                        {
                            "id": "DIG",
                            "level": 2
                        }
                    ],
                    [
                        {
                            "id": "HAMMER",
                            "level": 2
                        }
                    ],
                    [
                        {
                            "id": "SAW_W",
                            "level": 2
                        }
                    ]
                ],
                "components": [
                    [
                        [
                            "2x4",
                            41
                        ]
                    ],
                    [
                        [
                            "nail",
                            131
                        ]
                    ],
                    [
                        [
                            "wood_panel",
                            7
                        ]
                    ],
                    [
                        [
                            "hinge",
                            1
                        ]
                    ],
                    [
                        [
                            "glass_sheet",
                            1
                        ]
                    ],
                    [
                        [
                            "rock",
                            66
                        ]
                    ],
                    [
                        [
                            "pebble",
                            137
                        ]
                    ],
                    [
                        [
                            "mortar_build",
                            5
                        ]
                    ]
                ]
            }
        }
    },
    {
        "type": "recipe",
        "result": "faction_base_modular_workshop_room11to12_rock_southeast",
        "description": "Let's expand the workspace for larger projects and add a drop hammer for productivity.",
        "category": "CC_BUILDING",
        "subcategory": "CSC_BUILDING_BASES",
        "autolearn": false,
        "never_learn": true,
        "construction_blueprint": "fbmw_room11to12_rock_southeast",
        "blueprint_name": "openair, covered work space",
        "blueprint_requires": [
            {
                "id": "fbmw_northeast",
                "amount": 4
            }
        ],
        "blueprint_provides": [
            {
                "id": "fbmw_southeast"
            },
            {
                "id": "fbmw_south"
            },
            {
                "id": "blacksmith_recipes_7"
            }
        ],
        "blueprint_excludes": [
            {
                "id": "fbmw_northsoutheast"
            },
            {
                "id": "fbmw_south"
            }
        ],
        "blueprint_resources": [
            "wrench",
            "pliers",
            "fake_drop_hammer"
        ],
        "components": [
            [
                [
                    "wrench",
                    1
                ]
            ],
            [
                [
                    "pliers",
                    1
                ]
            ]
        ],
        "blueprint_needs": {
            "time": "1 s",
            "skills": [
                [
                    "fabrication",
                    6
                ],
                [
                    "survival",
                    2
                ]
            ],
            "inline": {
                "tools": [],
                "qualities": [
                    [
                        {
                            "id": "DIG",
                            "level": 2
                        }
                    ],
                    [
                        {
                            "id": "HAMMER",
                            "level": 2
                        }
                    ],
                    [
                        {
                            "id": "SAW_W",
                            "level": 2
                        }
                    ]
                ],
                "components": [
                    [
                        [
                            "metal_tank",
                            1
                        ]
                    ],
                    [
                        [
                            "water_faucet",
                            1
                        ]
                    ],
                    [
                        [
                            "anvil",
                            1
                        ]
                    ],
                    [
                        [
                            "chain",
                            1
                        ]
                    ],
                    [
                        [
                            "pipe",
                            1
                        ]
                    ],
                    [
                        [
                            "rock",
                            60
                        ]
                    ],
                    [
                        [
                            "pebble",
                            125
                        ]
                    ],
                    [
                        [
                            "mortar_build",
                            5
                        ]
                    ],
                    [
                        [
                            "wood_panel",
                            11
                        ]
                    ],
                    [
                        [
                            "2x4",
                            88
                        ]
                    ],
                    [
                        [
                            "nail",
                            220
                        ]
                    ]
                ]
            }
        }
    }
]